riemann_zyxel_gs1200/__init__.py
riemann_zyxel_gs1200/__main__.py
riemann_zyxel_gs1200-1.dist-info/LICENSE
riemann_zyxel_gs1200-1.dist-info/METADATA
riemann_zyxel_gs1200-1.dist-info/WHEEL
riemann_zyxel_gs1200-1.dist-info/entry_points.txt
riemann_zyxel_gs1200-1.dist-info/top_level.txt
riemann_zyxel_gs1200-1.dist-info/RECORD
