Metadata-Version: 2.1
Name: riemann-zyxel-gs1200
Version: 1
Summary: Send metrics to Riemann from Zyxel GS1200 PoE switches.
Home-page: https://github.com/mastensg/riemann-zyxel-gs1200
Author: Martin Stensgård
Author-email: mastensg@mastensg.net
License: UNKNOWN
Platform: UNKNOWN
Classifier: Programming Language :: Python :: 3
Classifier: License :: OSI Approved :: GNU Affero General Public License v3
Classifier: Operating System :: OS Independent
Requires-Dist: bernhard (>=0.2.6)
Requires-Dist: pyjsparser (>=2.5.2)
Requires-Dist: requests (>=2.21.0)
Requires-Dist: schedule (>=0.6.0)
